pyhuml/__init__.py
pyhuml/__metadata__.py
pyhuml-0.2.0.dist-info/licenses/LICENSE
pyhuml-0.2.0.dist-info/METADATA
pyhuml-0.2.0.dist-info/WHEEL
pyhuml-0.2.0.dist-info/top_level.txt
pyhuml-0.2.0.dist-info/RECORD
